protein/__init__.py
protein/buffer.py
protein/cli.py
protein/core.py
protein/dotenv.py
protein/error.py
protein/global_context.py
protein/import_modules.py
protein/protein_schema.yaml
protein/sql.py
protein/stack.py
protein/test.py
protein/util.py
protein_lang-0.6.1.dist-info/licenses/LICENSE
test/__init__.py
test/conftest.py
test/test_bindings.py
test/test_buffer.py
test/test_cli.py
test/test_define_local.py
test/test_dotenv.py
test/test_errors.py
test/test_eval.py
test/test_examples.py
test/test_exit.py
test/test_export.py
test/test_foreach.py
test/test_functions.py
test/test_globals.py
test/test_import.py
test/test_interpreter.py
test/test_literal_prefix.py
test/test_load.py
test/test_raw.py
test/test_sql.py
test/test_write.py
test/low_level/test_YAML_comments.py
test/low_level/test_bindings.py
test/low_level/test_buffer.py
test/low_level/test_dotenv.py
test/low_level/test_export_YAML.py
test/low_level/test_literal_prefix.py
test/low_level/test_markdown.py
test/low_level/test_quote.py
test/low_level/test_stack.py
test/low_level/test_to_functions.py
test/site_generator/module.py
test/site_generator/test_static_file_generator.py
test/source/import1.yaml
test/source/module1.py
test/source/test1.yaml
test/source/test2.yaml
test/source/test_function.yaml
test/source/test_module.yaml
yamlpp/__init__.py
protein_lang-0.6.1.dist-info/METADATA
protein_lang-0.6.1.dist-info/WHEEL
protein_lang-0.6.1.dist-info/entry_points.txt
protein_lang-0.6.1.dist-info/top_level.txt
protein_lang-0.6.1.dist-info/RECORD
