Metadata-Version: 2.4
Name: protein-lang
Version: 0.6.1
Summary: Protein: a macro language for data composition and templating
Author: Laurent
License: Copyright 2025 Laurent Franceschetti
Requires-Python: >=3.11
License-File: LICENSE
Requires-Dist: hjson>=3.1.0
Requires-Dist: jinja2>=3.1.6
Requires-Dist: jsonschema>=4.25.1
Requires-Dist: keyring>=25.7.0
Requires-Dist: markdown-it-py>=4.0.0
Requires-Dist: python-frontmatter>=1.1.0
Requires-Dist: rich>=14.2.0
Requires-Dist: ruamel-yaml>=0.18.16
Requires-Dist: sqlalchemy>=2.0.45
Requires-Dist: super-collections>=0.6.2
Requires-Dist: tomlkit>=0.13.3
Dynamic: license-file
